{
  "$schema": "https://schema.management.azure.com/schemas/2019-04-01/deploymentParameters.json#",
  "contentVersion": "1.0.0.0",
  "parameters": {
    "clusterName": { "value": "hpcuk1" },
    "headNodeOS": { "value": "WindowsServer2022" },
    "computeNodeImage": { "value": "WindowsServer2022" },
    "computeNodeNamePrefix": { "value": "hpcuk1" },

    "computeNodeNumber": { "value": 2 },
    "computeNodeVMSize": { "value": "Standard_D4s_v3" },
    "computeNodeOsDiskType": { "value": "Standard_SSD" },
    "computeNodeDataDiskSize": { "value": 128 },
    "computeNodeDataDiskCount": { "value": 0 },
    "computeNodeDataDiskType": { "value": "Standard_HDD" },

    "headNodeVMSize": { "value": "Standard_D8s_v3" },

    "enableAcceleratedNetworking": { "value": "No" },
    "createPublicIPAddressForHeadNode": { "value": "No" },

    "adminUsername": {
      "reference": {
        "keyVault": {
          "id": "/subscriptions/da883fd8-76c8-4ca5-a7e6-8567ae83ce10/resourceGroups/rg-numerica-uk/providers/Microsoft.KeyVault/vaults/key-vault-uk"
        },
        "secretName": "admin-username"
      }
    },
    "adminPassword": {
      "reference": {
        "keyVault": {
          "id": "/subscriptions/da883fd8-76c8-4ca5-a7e6-8567ae83ce10/resourceGroups/rg-numerica-uk/providers/Microsoft.KeyVault/vaults/key-vault-uk"
        },
        "secretName": "admin-password"
      }
    },

    "aadLoginEnabled": { "value": true },
    "authenticationKey": { "value": "" }
  }
}
